Metadata-Version: 1.0
Name: arid
Version: 0.1
Summary: Affinity Representing Instance Descriptors.
Home-page: https://github.com/funkelab/arid
Author: Jan Funke
Author-email: funkej@janelia.hhmi.org
License: MIT
Platform: UNKNOWN
